prompt_hyperopt/__init__.py
prompt_hyperopt/configurationspace.py
prompt_hyperopt/dataseteval.py
prompt_hyperopt/gpt.py
prompt_hyperopt/optimization.py
prompt_hyperopt/sampleevaluation.py
prompt_hyperopt/templatedprompt.py
prompt_hyperopt/test_gpt.py
prompt_hyperopt/test_greedy.py
prompt_hyperopt/test_optimizedprompt.py
prompt_hyperopt/test_sampleevaluation.py
prompt_hyperopt/test_templatedprompt.py
prompt_hyperopt-0.1.1.dist-info/LICENSE
prompt_hyperopt-0.1.1.dist-info/METADATA
prompt_hyperopt-0.1.1.dist-info/WHEEL
prompt_hyperopt-0.1.1.dist-info/top_level.txt
prompt_hyperopt-0.1.1.dist-info/RECORD
