Metadata-Version: 2.1
Name: prompt-hyperopt
Version: 0.1.1
Summary: Reliable language-model prompts through templates, calibration, and hyperparameter optimization
Home-page: https://github.com/Mavenoid/prompt-hyperopt
Author-email: Mavenoid <info@mavenoid.com>, Cenny Wenner <cwenner@gmail.com>
Project-URL: Source, https://github.com/Mavenoid/prompt-hyperopt
Project-URL: Tracker, https://github.com/Mavenoid/prompt-hyperopt/issues
Project-URL: Funding, https://www.mavenoid.com
Keywords: algorithm,configuration,hyperparameter optimization,machine learning,natural language processing
Classifier: Development Status :: 3 - Alpha
Classifier: Intended Audience :: Developers
Classifier: Intended Audience :: Science/Research
Classifier: License :: OSI Approved :: MIT License
Classifier: Natural Language :: English
Classifier: Operating System :: OS Independent
Classifier: Programming Language :: Python :: 3
Classifier: Programming Language :: Python :: 3.8
Classifier: Programming Language :: Python :: 3.9
Classifier: Programming Language :: Python :: 3.10
Classifier: Topic :: Scientific/Engineering :: Artificial Intelligence
Classifier: Topic :: Text Processing :: Linguistic
Classifier: Topic :: Utilities
License-File: LICENSE
Requires-Dist: datasets (>=2.6)
Requires-Dist: transformers (>=4.10)
Requires-Dist: configspace (>=0.6)
Requires-Dist: scipy (>=1.9)
Requires-Dist: openai (>=0.24)
Requires-Dist: jinja2 (>=1.2)
Requires-Dist: torch (>=1.13)
Requires-Dist: torchvision
Requires-Dist: torchaudio
Provides-Extra: dev
Requires-Dist: black (>=22.10.0) ; extra == 'dev'
Requires-Dist: build ; extra == 'dev'
Requires-Dist: check-manifest ; extra == 'dev'
Requires-Dist: pytest (>=3.0) ; extra == 'dev'
Requires-Dist: setuptools ; extra == 'dev'
Requires-Dist: tox (>=3.27) ; extra == 'dev'
Requires-Dist: tox-gh-actions (>=2.10) ; extra == 'dev'
Requires-Dist: twine ; extra == 'dev'
Requires-Dist: flake8 (>=5.0) ; extra == 'dev'
Requires-Dist: flake8-bugbear (>=22.10) ; extra == 'dev'
Requires-Dist: wheel ; extra == 'dev'
